click_creds/__init__.py
click_creds/classes.py
click_creds/decorators.py
click_creds/defaults.py
click_creds/groups.py
click_creds/utils.py
click_creds-0.0.3.dist-info/LICENSE
click_creds-0.0.3.dist-info/METADATA
click_creds-0.0.3.dist-info/WHEEL
click_creds-0.0.3.dist-info/top_level.txt
click_creds-0.0.3.dist-info/RECORD
