Metadata-Version: 2.1
Name: click-creds
Version: 0.0.3
Summary: Pluggable credentials storage and management for click CLI apps.
Home-page: https://github.com/eshaan7/click-creds
Author: Eshaan Bansal
Author-email: eshaan7bansal@gmail.com
License: BSD
Project-URL: Documentation, https://github.com/eshaan7/click-creds
Project-URL: Funding, https://www.paypal.me/eshaanbansal
Project-URL: Source, https://github.com/eshaan7/click-creds
Project-URL: Tracker, https://github.com/eshaan7/click-creds/issues
Keywords: click credentials creds netrc auth cli python store
Platform: UNKNOWN
Classifier: Development Status :: 5 - Production/Stable
Classifier: Intended Audience :: Developers
Classifier: Environment :: Web Environment
Classifier: License :: OSI Approved :: BSD License
Classifier: Programming Language :: Python :: 3
Classifier: Programming Language :: Python :: 3.6
Classifier: Programming Language :: Python :: 3.7
Classifier: Programming Language :: Python :: 3.8
Classifier: Programming Language :: Python :: 3.9
Classifier: Programming Language :: Python :: 3.10
Classifier: Topic :: Software Development :: Libraries :: Python Modules
Requires-Python: >=3.6
Provides-Extra: dev
Provides-Extra: test
License-File: LICENSE
